LICENSE.txt
README.rst
dcat_swift_operator.py
pyproject.toml
amsterdam_airflow_dcat_swift_operator.egg-info/PKG-INFO
amsterdam_airflow_dcat_swift_operator.egg-info/SOURCES.txt
amsterdam_airflow_dcat_swift_operator.egg-info/dependency_links.txt
amsterdam_airflow_dcat_swift_operator.egg-info/requires.txt
amsterdam_airflow_dcat_swift_operator.egg-info/top_level.txt