Metadata-Version: 2.1
Name: amsterdam-airflow-dcat-swift-operator
Version: 0.1
Summary: Amsterdam Airflow operator: dcat_swift_operator
Author: Amsterdam
Author-email: welcome@amsterdam.nl
Maintainer-email: Amsterdam <welcome@amsterdam.nl>
Project-URL: homepage, https://www.amsterdam.nl/
Project-URL: documentation, https://readthedocs.example.com
Project-URL: repository, https://example.com/git
Project-URL: changelog, https://example.com/git/Amsterdam/blob/master/CHANGELOG.md
Classifier: Programming Language :: Python
Requires-Python: >=3.9
License-File: LICENSE.txt
